tests/test_filterlib.py
bbf-0.2.0.dist-info/top_level.txt
bbf-0.2.0.dist-info/METADATA
bbf-0.2.0.dist-info/WHEEL
bbf-0.2.0.dist-info/LICENSE
bbf-0.2.0.dist-info/RECORD
bbf/bspline.py
bbf/magsys.py
bbf/sncosmoutils.py
bbf/splineutils.py
bbf/_libbbf.cpython-311-x86_64-linux-gnu.so
bbf/snfilterset.py
bbf/filterlib.py
bbf/filterset.py
bbf/__init__.py
bbf/utils.c
bbf/stellarlib/calspec.py
bbf/stellarlib/pickles.py
bbf/stellarlib/__init__.py
examples/fluxes.py
examples/ex_magsys.py
examples/bandpasses.py
examples/mags.py
examples/bs_max.py
examples/gaia.py
examples/basics.py
examples/bbf_sncosmo.py
