Metadata-Version: 2.1
Name: bbf
Version: 0.2.0
Summary: Fast computation of broadband fluxes and mags
Home-page: https://gitlab.in2p3.fr/lemaitre/bbf
Author: Nicolas Regnault
Author-email: nicolas.regnault@lpnhe.in2p3.fr
License: MIT
Keywords: astronomy,astrophysics
Classifier: Development Status :: 2 - Pre-Alpha
Classifier: Intended Audience :: Science/Research
Classifier: License :: OSI Approved :: Apache Software License
Classifier: Programming Language :: Python :: 3
Classifier: Topic :: Scientific/Engineering :: Astronomy
Classifier: Topic :: Scientific/Engineering :: Physics
Requires-Python: >=3.8
License-File: LICENSE
Requires-Dist: numpy
Requires-Dist: pandas
Requires-Dist: scipy
Requires-Dist: scikit-sparse
Requires-Dist: matplotlib
Requires-Dist: platformdirs
Requires-Dist: sncosmo
Requires-Dist: astropy
Requires-Dist: getCalspec
Requires-Dist: importlib-resources ; python_version < "3.9"
